browsergym/miniwob/__init__.py
browsergym/miniwob/all.py
browsergym/miniwob/base.py
browsergym_miniwob-0.14.3.dist-info/METADATA
browsergym_miniwob-0.14.3.dist-info/WHEEL
browsergym_miniwob-0.14.3.dist-info/RECORD
